eikon_api_wrapper/__init__.py
eikon_api_wrapper/docs/images/eikon_front_end_pic1.PNG
eikon_api_wrapper/docs/images/eikon_front_end_pic2.PNG
eikon_api_wrapper/eikon_data_extractor.py
eikon_api_wrapper/session.py
eikon_api_wrapper-0.0.5.dist-info/LICENSE
eikon_api_wrapper-0.0.5.dist-info/METADATA
eikon_api_wrapper-0.0.5.dist-info/WHEEL
eikon_api_wrapper-0.0.5.dist-info/RECORD
