Metadata-Version: 2.1
Name: eikon_api_wrapper
Version: 0.0.5
Summary: Enables effective and resilient Eikon data extracts.
License: MIT
Keywords: eikon,api,wrapper,data,extracts
Author: Marcus Rockel
Author-email: marcus.rockel@finance.uni-freiburg.de
Requires-Python: >=3.9,<4.0
Classifier: License :: OSI Approved :: MIT License
Classifier: Programming Language :: Python :: 3
Classifier: Programming Language :: Python :: 3.9
Classifier: Programming Language :: Python :: 3.10
Classifier: Programming Language :: Python :: 3.11
Classifier: Programming Language :: Python :: 3.12
Requires-Dist: eikon (>=1.1.18,<2.0.0)
Requires-Dist: pandas (>=2.2.1,<3.0.0)
